area_calculator_Kraetzi.py
area_calculator_Kraetzi-0.0.1.dist-info/LICENSE
area_calculator_Kraetzi-0.0.1.dist-info/METADATA
area_calculator_Kraetzi-0.0.1.dist-info/WHEEL
area_calculator_Kraetzi-0.0.1.dist-info/top_level.txt
area_calculator_Kraetzi-0.0.1.dist-info/RECORD
