Metadata-Version: 2.1
Name: area-calculator-Kraetzi
Version: 0.0.1
Summary: Calculate areas of geometrical figures
Author: Kajo Nikolaev Studenov
Classifier: Programming Language :: Python :: 3
Classifier: License :: OSI Approved :: MIT License
Classifier: Operating System :: OS Independent
Requires-Python: >=3.8
License-File: LICENSE
